Workbook
Name Slicer_category: #N/A
Name Slicer_Date_Hierarchy: #N/A
Name Slicer_payment_method: #N/A
Name Slicer_state: #N/A
Name Timeline_Date: #N/A

Sheet Sheet1
A1: Row Labels | B1: Sum of Revenue | E1: Row Labels | F1: Sum of Revenue | G1: Profit_Margin1 | I1: Row Labels | J1: Sum of Revenue
A2: Lucknow | B2: 2848356 | E2: Tablet | F2: 1944000 | G2: 0.25 | I2: Madhya Pradesh | J2: 4149601 | L2: Row Labels | M2: Repeat Customers | V2: Row Labels | W2: Top 5 Product Sales
A3: Indore | B3: 2799145 | E3: Office Chair | F3: 790500 | G3: 0.29411765 | I3: Rajasthan | J3: 3636899 | L3: Rajasthan | M3: 7 | V3: Laptop | W3: 5830000
A4: Kota | B4: 2026546 | E4: Monitor | F4: 1675000 | G4: 0.28 | I4: Uttar Pradesh | J4: 2848356 | L4: Madhya Pradesh | M4: 7 | V4: Mobile Phone | W4: 2575000
A5: Delhi | B5: 1940744 | E5: Mobile Phone | F5: 2575000 | G5: 0.24 | I5: Delhi | J5: 1940744 | L5: Uttar Pradesh | M5: 4 | V5: Monitor | W5: 1675000
A6: Chandigarh | B6: 1520663 | E6: Laptop | F6: 5830000 | G6: 0.23636364 | I6: Chandigarh | J6: 1520663 | L6: Tamil Nadu | M6: 4 | V6: Office Chair | W6: 790500
A7: Chennai | B7: 1476942 | E7: Grand Total | F7: 12814500 | G7: 0.24842951 | I7: Tamil Nadu | J7: 1476942 | L7: Delhi | M7: 4 | V7: Tablet | W7: 1944000
A8: Bengaluru | B8: 1466768 | I8: Karnataka | J8: 1466768 | L8: Karnataka | M8: 3 | V8: Grand Total | W8: 20542154
A9: Bhopal | B9: 1350456 | I9: Gujarat | J9: 1462843 | L9: Gujarat | M9: 3
A10: Udaipur | B10: 1194057 | I10: West Bengal | J10: 822086 | L10: Telangana | M10: 2
A11: Surat | B11: 1031161 | I11: Telangana | J11: 654675 | L11: Chandigarh | M11: 2
A12: Kolkata | B12: 822086 | I12: Maharashtra | J12: 311878 | L12: Maharashtra | M12: 2
A13: Hyderabad | B13: 654675 | I13: Bihar | J13: 250699 | L13: West Bengal | M13: 1
A14: Ahmedabad | B14: 431682 | I14: Grand Total | J14: 20542154 | L14: Bihar | M14: 1
A15: Jodhpur | B15: 416296 | L15: Grand Total | M15: 40
A16: Patna | B16: 250699
A17: Pune | B17: 217986
A18: Mumbai | B18: 93892
A19: Grand Total | B19: 20542154
A30: Row Labels | B30: Sum of Revenue | E30: Column Labels
A31: Paid | E31: Q1 | G31: Q2 | I31: Q3 | K31: Q4 | M31: Total Sum of Revenue | N31: Total Profit_Margin1
A32: Accessories | B32: 1110399 | D32: Row Labels | E32: Sum of Revenue | F32: Profit_Margin1 | G32: Sum of Revenue | H32: Profit_Margin1 | I32: Sum of Revenue | J32: Profit_Margin1 | K32: Sum of Revenue | L32: Profit_Margin1
A33: Electronics | B33: 11657600 | D33: Ahmedabad | I33: 27300 | J33: 0.38095238 | K33: 404382 | L33: 0.32155734 | M33: 431682 | N33: 0.32531354
A34: Fashion | B34: 1418323 | D34: Bengaluru | G34: 204596 | H34: 0.32207863 | I34: 619690 | J34: 0.28706289 | K34: 642482 | L34: 0.30200379 | M34: 1466768 | N34: 0.29849165
A35: Furniture | B35: 1810500 | D35: Bhopal | E35: 60500 | F35: 0.29586777 | G35: 417081 | H35: 0.2867093 | I35: 228493 | J35: 0.34155532 | K35: 644382 | L35: 0.30142369 | M35: 1350456 | N35: 0.30342047
A36: Home | B36: 91000 | D36: Chandigarh | E36: 54689 | F36: 0.44047249 | G36: 191599 | H36: 0.33141613 | I36: 381289 | J36: 0.2998749 | K36: 893086 | L36: 0.2942449 | M36: 1520663 | N36: 0.30559894
A37: Home Appliances | B37: 1532200 | D37: Chennai | G37: 558390 | H37: 0.28249073 | I37: 489766 | J37: 0.31457063 | K37: 428786 | L37: 0.37218099 | M37: 1476942 | N37: 0.31916758
A38: Pending | D38: Delhi | G38: 329893 | H38: 0.27203669 | I38: 721590 | J38: 0.28532823 | K38: 889261 | L38: 0.33371642 | M38: 1940744 | N38: 0.30524067
A39: Accessories | B39: 18696 | D39: Hyderabad | I39: 43798 | J39: 0.39494954 | K39: 610877 | L39: 0.33358106 | M39: 654675 | N39: 0.33768664
A40: Electronics | B40: 238200 | D40: Indore | E40: 90800 | F40: 0.27973568 | G40: 97296 | H40: 0.27232363 | I40: 1002393 | J40: 0.26580692 | K40: 1608656 | L40: 0.30709238 | M40: 2799145 | N40: 0.29021183
A41: Fashion | B41: 48595 | D41: Jodhpur | I41: 364296 | J41: 0.30715682 | K41: 52000 | L41: 0.30192308 | M41: 416296 | N41: 0.30650307
A42: Furniture | B42: 18000 | D42: Kolkata | I42: 408699 | J42: 0.30878226 | K42: 413387 | L42: 0.33851331 | M42: 822086 | N42: 0.32373255
A43: Home | B43: 1400 | D43: Kota | E43: 165000 | F43: 0.23636364 | G43: 264190 | H43: 0.31734736 | I43: 714075 | J43: 0.30434478 | K43: 883281 | L43: 0.29495823 | M43: 2026546 | N43: 0.2964137
A44: Home Appliances | B44: 39000 | D44: Lucknow | E44: 4400 | F44: 0.45454545 | G44: 162091 | H44: 0.34203626 | I44: 1110089 | J44: 0.27271597 | K44: 1571776 | L44: 0.28749389 | M44: 2848356 | N44: 0.28509639
A45: Refunded | D45: Mumbai | I45: 13200 | J45: 0.45454545 | K45: 80692 | L45: 0.35185644 | M45: 93892 | N45: 0.36629319
A46: Accessories | B46: 130074 | D46: Patna | G46: 23400 | H46: 0.33760684 | I46: 158199 | J46: 0.39190513 | K46: 69100 | L46: 0.27062229 | M46: 250699 | N46: 0.35340787
A47: Electronics | B47: 1600300 | D47: Pune | K47: 217986 | L47: 0.36601433 | M47: 217986 | N47: 0.36601433
A48: Fashion | B48: 187367 | D48: Surat | G48: 247400 | H48: 0.27445432 | I48: 100099 | J48: 0.34414929 | K48: 683662 | L48: 0.30250621 | M48: 1031161 | N48: 0.29981836
A49: Furniture | B49: 300500 | D49: Udaipur | G49: 188793 | H49: 0.30956127 | I49: 491374 | J49: 0.3423543 | K49: 513890 | L49: 0.27105022 | M49: 1194057 | N49: 0.30648202
A50: Home | B50: 23800 | D50: Grand Total | E50: 375389 | F50: 0.28873782 | G50: 2684729 | H50: 0.29667017 | I50: 6874350 | J50: 0.29867551 | K50: 10607686 | L50: 0.30885492 | M50: 20542154 | N50: 0.30348833
A51: Home Appliances | B51: 316200
A52: Grand Total | B52: 20542154
O60: Column Labels
O61: January | P61: February | Q61: March | R61: April | S61: May | T61: June | U61: July | V61: August | W61: September | X61: October | Y61: November | Z61: December | AA61: Grand Total
N62: AOV | O62: 15.780596 | P62: 41.351621 | Q62: 16.573663 | R62: 36.435518 | S62: 35.730524 | T62: 30.346198 | U62: 27.422315 | V62: 35.716361 | W62: 44.257099 | X62: 28.493738 | Y62: 30.679358 | Z62: 30.387842 | AA62: 32.542026
O65: Column Labels
O66: January | P66: February | Q66: March | R66: April | S66: May | T66: June | U66: July | V66: August | W66: September | X66: October | Y66: November | Z66: December
N67: AOV | O67: =GETPIVOTDATA("[Measures].[AOV]",$N$60,"[Calendar].[Month]","[Calendar].[Month].&[January]") -> 15.780596 | P67: =GETPIVOTDATA("[Measures].[AOV]",$N$60,"[Calendar].[Month]","[Calendar].[Month].&[January]") -> 15.780596 | Q67: =GETPIVOTDATA("[Measures].[AOV]",$N$60,"[Calendar].[Month]","[Calendar].[Month].&[March]") -> 16.573663 | R67: =GETPIVOTDATA("[Measures].[AOV]",$N$60,"[Calendar].[Month]","[Calendar].[Month].&[March]") -> 16.573663 | S67: =GETPIVOTDATA("[Measures].[AOV]",$N$60,"[Calendar].[Month]","[Calendar].[Month].&[May]") -> 35.730524 | T67: =GETPIVOTDATA("[Measures].[AOV]",$N$60,"[Calendar].[Month]","[Calendar].[Month].&[June]") -> 30.346198 | U67: =GETPIVOTDATA("[Measures].[AOV]",$N$60,"[Calendar].[Month]","[Calendar].[Month].&[July]") -> 27.422315 | V67: =GETPIVOTDATA("[Measures].[AOV]",$N$60,"[Calendar].[Month]","[Calendar].[Month].&[August]") -> 35.716361 | W67: =GETPIVOTDATA("[Measures].[AOV]",$N$60,"[Calendar].[Month]","[Calendar].[Month].&[September]") -> 44.257099 | X67: =GETPIVOTDATA("[Measures].[AOV]",$N$60,"[Calendar].[Month]","[Calendar].[Month].&[October]") -> 28.493738 | Y67: =GETPIVOTDATA("[Measures].[AOV]",$N$60,"[Calendar].[Month]","[Calendar].[Month].&[November]") -> 30.679358 | Z67: =GETPIVOTDATA("[Measures].[AOV]",$N$60,"[Calendar].[Month]","[Calendar].[Month].&[December]") -> 30.387842
A72: Row Labels | B72: AOV | D72: Row Labels | E72: Profit_Margin1 | G72: Row Labels | H72: ASP
A73: Indore | B73: 44.168665 | D73: Mumbai | E73: 0.36629319 | G73: Electronics | H73: 11107.901
A74: Lucknow | B74: 41.15824 | D74: Pune | E74: 0.36601433 | G74: Furniture | H74: 6912.3377
A75: Udaipur | B75: 35.544816 | D75: Patna | E75: 0.35340787 | G75: Home Appliances | H75: 6030.0319
A76: Bengaluru | B76: 35.509805 | D76: Hyderabad | E76: 0.33768664 | G76: Fashion | H76: 2529.4878
A77: Chandigarh | B77: 34.11241 | D77: Ahmedabad | E77: 0.32531354 | G77: Accessories | H77: 2001.8585
A78: Jodhpur | B78: 33.936252 | D78: Kolkata | E78: 0.32373255 | G78: Home | H78: 1400
A79: Delhi | B79: 33.340388 | D79: Chennai | E79: 0.31916758 | G79: Grand Total | H79: 6415.4135
A80: Kota | B80: 32.377077 | D80: Jodhpur | E80: 0.30650307
A81: Surat | B81: 31.724126 | D81: Udaipur | E81: 0.30648202
A82: Bhopal | B82: 31.340357 | D82: Chandigarh | E82: 0.30559894
A83: Kolkata | B83: 28.502098 | D83: Delhi | E83: 0.30524067
A84: Chennai | B84: 24.209783 | D84: Bhopal | E84: 0.30342047
A85: Hyderabad | B85: 23.520694 | D85: Surat | E85: 0.29981836
A86: Ahmedabad | B86: 21.714386 | D86: Bengaluru | E86: 0.29849165
A87: Patna | B87: 20.256868 | D87: Kota | E87: 0.2964137
A88: Pune | B88: 17.258016 | D88: Indore | E88: 0.29021183
A89: Mumbai | B89: 11.793996 | D89: Lucknow | E89: 0.28509639
A90: Grand Total | B90: 32.542026 | D90: Grand Total | E90: 0.30348833
G100: Column Labels
B101: Row Labels | C101: AOV | G101: January | H101: February | I101: March | J101: April | K101: May | L101: June | M101: July | N101: August | O101: September | P101: October | Q101: November | R101: December | S101: Grand Total
B102: Indore | C102: 44.168665 | F102: Sum of Revenue | G102: 39199 | H102: 252493 | I102: 83697 | J102: 785987 | K102: 863178 | L102: 1035564 | M102: 1275549 | N102: 1856465 | O102: 3742336 | P102: 2943802 | Q102: 2600996 | R102: 5062888 | S102: 20542154
B103: Lucknow | C103: 41.15824
B104: Udaipur | C104: 35.544816
B105: Bengaluru | C105: 35.509805
B106: Chandigarh | C106: 34.11241
B107: Jodhpur | C107: 33.936252
B108: Delhi | C108: 33.340388
B109: Kota | C109: 32.377077
B110: Surat | C110: 31.724126
B111: Bhopal | C111: 31.340357 | J111: Row Labels | K111: Sum of Revenue
B112: Kolkata | C112: 28.502098 | J112: Electronics | K112: 13496100
B113: Chennai | C113: 24.209783 | J113: Furniture | K113: 2129000
B114: Hyderabad | C114: 23.520694 | J114: Home Appliances | K114: 1887400
B115: Ahmedabad | C115: 21.714386 | J115: Fashion | K115: 1654285
B116: Patna | C116: 20.256868 | J116: Accessories | K116: 1259169
B117: Pune | C117: 17.258016 | J117: Home | K117: 116200
B118: Mumbai | C118: 11.793996 | J118: Grand Total | K118: 20542154
B119: Grand Total | C119: 32.542026

Sheet Sheet3
A1: Total MTD | C1: Total YTD | E1: Total QTD | G1: Repeat Customers | J1: ASP | L1: Unic Product Sold | O1: Profit_Margin1
A2: 5062888 | C2: 20542154 | E2: 10607686 | G2: 40 | J2: 6415.4135 | L2: 30 | O2: 0.30348833
A3: =GETPIVOTDATA("[Measures].[Total MTD]",$A$1) -> 5062888 | C3: =GETPIVOTDATA("[Measures].[Total YTD]",$C$1) -> 20542154 | E3: =GETPIVOTDATA("[Measures].[Total QTD]",$E$1) -> 10607686 | G3: =GETPIVOTDATA("[Measures].[Repeat Customers]",$G$1) -> 40 | J3: =GETPIVOTDATA("[Measures].[ASP]",$J$1) -> 6415.4135 | L3: =GETPIVOTDATA("[Measures].[Unic Product Sold]",$L$1) -> 30 | O3: =GETPIVOTDATA("[Measures].[Profit_Margin1]",$O$1) -> 0.30348833
N7: Return Rate %
N8: 0.05464396
O11: Total Customers
O12: 500
A14: Total_Profit | C14: AOV | E14: Total_Profit | G14: Total_Quantity | J14: Total_Profit | K14: Total_Sales | M14: Product Sales Rank
A15: 6234304 | C15: 32.542026 | E15: 6234304 | G15: 3202 | J15: 6234304 | K15: 20542154 | M15: 1
A16: =GETPIVOTDATA("[Measures].[Total_Profit]",$A$14) -> 6234304 | C16: =GETPIVOTDATA("[Measures].[AOV]",$C$14) -> 32.542026 | G16: =GETPIVOTDATA("[Measures].[Total_Quantity]",$G$14) -> 3202 | J16: =GETPIVOTDATA("[Measures].[Total_Profit]",$J$14) -> 6234304 | M16: =GETPIVOTDATA("[Measures].[Product Sales Rank]",$M$14) -> 1 | O16: Row Labels | P16: Sales Contribution %
O17: Laptop | P17: 0.28380665
O18: Mobile Phone | P18: 0.125352
O19: Tablet | P19: 0.094634672
O20: Monitor | P20: 0.081539648
O21: Office Chair | P21: 0.038481846
O22: Desk | P22: 0.035439322
O23: Coffee Maker | P23: 0.034806476
O24: Air Fryer | P24: 0.030668644
A25: Sales YoY % | C25: Sales Previous Year | O25: Bookshelf | P25: 0.029719376
O26: Mixer Grinder | P26: 0.026404242
A27: =GETPIVOTDATA("[Measures].[Sales YoY %]",$A$25) -> 0 | C27: =GETPIVOTDATA("[Measures].[Sales Previous Year]",$C$25) -> 0 | O27: Grand Total | P27: 0.78085287

Sheet Sheet2

Sheet Sheet4
A1: Total Sales | B1: Sales Previous Year | D1: Total Profit | E1: Porfit Margin | G1: AOV | I1: ASP | K1: Total YTD | M1: Total MTD | O1: Total QTD | Q1: RepeatCustomers | S1: Sales YoY Growth | U1: Orders Return Rate | V1: Total Customers
A2: =GETPIVOTDATA("[Measures].[Total_Sales]",Sheet3!$J$14) -> 20542154 | B2: =GETPIVOTDATA("[Measures].[Sales Previous Year]",Sheet3!$C$25) -> 0 | D2: =GETPIVOTDATA("[Measures].[Total_Profit]",Sheet3!$E$14) -> 6234304 | E2: =GETPIVOTDATA("[Measures].[Profit_Margin1]",Sheet3!$O$1) -> 0.30348833 | G2: =GETPIVOTDATA("[Measures].[AOV]",Sheet3!$C$14) -> 32.542026 | I2: =GETPIVOTDATA("[Measures].[ASP]",Sheet3!$J$1) -> 6415.4135 | K2: =GETPIVOTDATA("[Measures].[Total YTD]",Sheet3!$C$1) -> 20542154 | M2: =GETPIVOTDATA("[Measures].[Total MTD]",Sheet3!$A$1) -> 5062888 | O2: =GETPIVOTDATA("[Measures].[Total QTD]",Sheet3!$E$1) -> 10607686 | Q2: =GETPIVOTDATA("[Measures].[Repeat Customers]",Sheet3!$G$1) -> 40 | S2: =GETPIVOTDATA("[Measures].[Sales YoY %]",Sheet3!$A$25) -> 0 | U2: =GETPIVOTDATA("[Measures].[Return Rate %]",Sheet3!$N$7) -> 0.05464396 | V2: =GETPIVOTDATA("[Measures].[Total Customers]",Sheet3!$O$11) -> 500
